labtech/__init__.py
labtech/cache.py
labtech/diagram.py
labtech/exceptions.py
labtech/lab.py
labtech/monitor.py
labtech/mypy_plugin.py
labtech/py.typed
labtech/serialization.py
labtech/storage.py
labtech/tasks.py
labtech/types.py
labtech/utils.py
labtech/runners/__init__.py
labtech/runners/_process_executor.py
labtech/runners/base.py
labtech/runners/process.py
labtech/runners/ray.py
labtech/runners/serial.py
labtech/runners/thread.py
labtech-1.0.0.dist-info/METADATA
labtech-1.0.0.dist-info/WHEEL
labtech-1.0.0.dist-info/licenses/LICENSE
labtech-1.0.0.dist-info/RECORD
