Metadata-Version: 2.4
Name: labtech
Version: 1.0.0
Summary: Easily run experiment permutations with multi-processing and caching.
Project-URL: repository, https://github.com/ben-denham/labtech
Author-email: Ben Denham <ben@denham.nz>
License-Expression: GPL-3.0-only
License-File: LICENSE
Classifier: Development Status :: 2 - Pre-Alpha
Classifier: Intended Audience :: Developers
Classifier: Intended Audience :: Science/Research
Classifier: License :: OSI Approved :: GNU General Public License v3 (GPLv3)
Classifier: Topic :: Software Development :: Libraries :: Python Modules
Requires-Python: <4.0,>=3.11
Requires-Dist: frozendict>=2.4.0
Requires-Dist: psutil>=7.0.0
Requires-Dist: tqdm>=4.66.2
